Workbook

Sheet 1. Cover
B2: ACCOUNTING WORK SIMULATION EXERCISE (PT MAJU BERSAMA)
B3: Simulasi Proyek Nyata Akuntansi Perusahaan & Soal Ujian Tes Kerja Staf Akunting
B5: Nama Perusahaan | C5: PT MAJU BERSAMA / CV MAJU BERSAMA
B6: Bidang Usaha | C6: Jasa Konsultasi Bisnis & Perdagangan
B7: Periode Laporan | C7: Januari 2025 (Siklus Penuh) & Mei 2024 (Kasus Tes Interview)
B8: Standar Pembukuan | C8: Basis Akrual (Accrual Basis) & PSAK / SAK Indonesia
B9: Tarif PPN Berlaku | C9: 11% (PPN Keluaran atas Penjualan & PPN Masukan Pembelian)
B10: Metode Depresiasi | C10: Garis Lurus (Straight Line Method / SLN)
B11: Tujuan Pelatihan | C11: Mempersiapkan staf akunting menghadapi tes kerja interview dan praktik software ERP/Excel nyata
B14: DAFTAR LEMBAR KERJA DALAM WORKBOOK INI:
B15: Nama Sheet | C15: Keterangan Isi Sheet & Praktik
B16: 2. Soal_Interview_Akunting | C16: 8 Soal transaksi tes interview kerja akunting (CV Maju Bersama) persis lembar tes kerja
B17: 3. Dokumen_Transaksi | C17: Daftar 10 dokumen transaksi riil PT Maju Bersama (Bukti Kas Masuk, Keluar, Faktur Pajak PPN)
B18: 4. Jurnal_Umum | C18: Jurnal umum lengkap dengan kolom Debet, Kredit, PPN, dan formula keseimbangan
B19: 5. Buku_Besar | C19: Buku besar 4 kolom (T-Account) akun Kas, Piutang, Perlengkapan, Peralatan, Utang, & Modal
B20: 6. Neraca_Saldo | C20: Neraca saldo sebelum penyesuaian dengan formula SUM & Cek Balance otomatis
B21: 7. Jurnal_Penyesuaian | C21: Jurnal penyesuaian (AJP): Sewa dimuka, depresiasi SLN, bunga akrual, rekonsiliasi bank
B22: 8. Kertas_Kerja_10_Kolom | C22: Worksheet / Neraca Lajur 10 Kolom lengkap dari Neraca Saldo sampai Neraca Akhir
B23: 9. Laporan_Laba_Rugi | C23: Laporan laba rugi komprehensif (Pendapatan vs Beban Operasional)
B24: 10. Laporan_Perubahan_Modal | C24: Laporan perubahan ekuitas pemilik
B25: 11. Neraca_Keuangan | C25: Laporan posisi keuangan (Neraca: Aktiva vs Pasiva)
B26: 99_KUNCI_JAWABAN | C26: Kunci jawaban resmi, rumus Excel lengkap, dan penjelasan analisis akuntansi

Sheet 2. Soal_Interview_Akunting
B2: SOAL INTERVIEW - AKUNTING: JURNAL TRANSAKSI SEDERHANA
B3: Waktu Pengerjaan: 15 Menit | Dilarang menggunakan kalkulator dan internet | Sistem Akrual
B5: Nama Perusahaan | C5: : CV Maju Bersama
B6: Bidang Usaha | C6: : Perdagangan
B7: Periode | C7: : Mei 2024
B9: Daftar Transaksi untuk Dijurnal:
B10: 1. 1 Mei 2024 - Pemilik menyetor uang tunai ke perusahaan sebesar Rp50.000.000.
B11: 2. 2 Mei 2024 - Perusahaan membeli perlengkapan kantor secara tunai Rp3.500.000.
B12: 3. 3 Mei 2024 - Perusahaan membeli barang dagangan secara kredit dari PT Sumber Jaya sebesar Rp15.000.000.
B13: 4. 5 Mei 2024 - Perusahaan menjual barang dagangan secara tunai sebesar Rp8.000.000.
B14: 5. 7 Mei 2024 - Perusahaan menerima pembayaran dari pelanggan atas penjualan kredit tanggal 5 Mei sebesar Rp8.000.000.
B15: 6. 10 Mei 2024 - Perusahaan membayar sebagian utang kepada PT Sumber Jaya sebesar Rp5.000.000 secara transfer bank.
B16: 7. 12 Mei 2024 - Perusahaan membayar beban listrik dan air sebesar Rp750.000 secara tunai.
B17: 8. 15 Mei 2024 - Perusahaan menarik uang tunai untuk keperluan pribadi pemilik (prive) sebesar Rp2.000.000.
B19: Format Jurnal yang Digunakan (Lembar Pengerjaan Tes Peserta):
B20: Tanggal | C20: Akun Debet | D20: Debet (Rp) | E20: Akun Kredit | F20: Kredit (Rp) | G20: Cek Baris
G21: =IF(D21=F21, "✓ Balance", "Cek")
G22: =IF(D22=F22, "✓ Balance", "Cek")
G23: =IF(D23=F23, "✓ Balance", "Cek")
G24: =IF(D24=F24, "✓ Balance", "Cek")
G25: =IF(D25=F25, "✓ Balance", "Cek")
G26: =IF(D26=F26, "✓ Balance", "Cek")
G27: =IF(D27=F27, "✓ Balance", "Cek")
G28: =IF(D28=F28, "✓ Balance", "Cek")
B29: TOTAL | D29: =SUM(D21:D28) | F29: =SUM(F21:F28) | G29: =IF(D29=F29, "✓ BALANCE", "⚠️ TIDAK BALANCE")

Sheet 3. Dokumen_Transaksi
B2: PT MAJU BERSAMA - DOKUMEN TRANSAKSI
B3: Periode: Januari 2025
B5: No. Bukti | C5: Keterangan Transaksi | D5: Jumlah (Rp) | E5: Jenis Bukti | F5: Kode Akun Terkait
B6: KM-001 | C6: Pemilik menyetor modal awal tunai | D6: 100000000 | E6: Bukti Kas Masuk | F6: 1-101 / 3-101
B7: KM-002 | C7: Diterima pinjaman bank (Kredit Modal Kerja) | D7: 50000000 | E7: Bukti Kas Masuk | F7: 1-101 / 2-101
B8: BK-001 | C8: Dibayar sewa gedung untuk 3 tahun (Jan-Des) | D8: 24000000 | E8: Bukti Kas Keluar | F8: 1-105 / 1-101
B9: BK-002 | C9: Dibeli perlengkapan kantor secara tunai | D9: 6500000 | E9: Bukti Kas Keluar | F9: 1-104 / 1-101
B10: FJ-001 | C10: Dijual jasa konsultasi kepada PT ABC (kredit) | D10: 35000000 | E10: Faktur Penjualan + PPN | F10: 1-102 / 4-101 / 2-104
B11: FJ-002 | C11: Dijual jasa konsultasi kepada CV DEF (kredit) | D11: 8800000 | E11: Faktur Penjualan + PPN | F11: 1-102 / 4-101 / 2-104
B12: FB-001 | C12: Dibeli peralatan kantor dari CV XYZ (kredit) | D12: 13320000 | E12: Faktur Pembelian + PPN | F12: 1-103 / 1-106 / 2-102
B13: KM-003 | C13: Diterima pelunasan piutang dari PT ABC | D13: 15000000 | E13: Bukti Kas Masuk | F13: 1-101 / 1-102
B14: BK-003 | C14: Dibayar gaji karyawan bulan Januari | D14: 6500000 | E14: Bukti Kas Keluar | F14: 5-101 / 1-101
B15: BK-004 | C15: Dibayar biaya listrik dan telepon | D15: 1200000 | E15: Bukti Kas Keluar | F15: 5-102 / 1-101
B16: TOTAL TRANSAKSI | D16: =SUM(D6:D15)

Sheet 4. Jurnal_Umum
B2: PT MAJU BERSAMA - JURNAL UMUM
B3: Periode: Januari 2025
B5: Tgl | C5: No. Bukti | D5: Kode Akun | E5: Nama Akun | F5: Ref | G5: Debet (Rp) | H5: Kredit (Rp) | I5: Keterangan PPN
B6: 01/01 | C6: KM-001 | D6: 1-101 | E6: Kas | F6: ✓ | G6: 100000000 | H6: 0 | I6: Setoran Modal Awal
B7: 01/01 | C7: KM-001 | D7: 3-101 | E7: Modal Pemilik | F7: ✓ | G7: 0 | H7: 100000000
B8: 02/01 | C8: KM-002 | D8: 1-101 | E8: Kas | F8: ✓ | G8: 50000000 | H8: 0 | I8: Pencairan Pinjaman Bank
B9: 02/01 | C9: KM-002 | D9: 2-101 | E9: Utang Bank (KMK) | F9: ✓ | G9: 0 | H9: 50000000
B10: 03/01 | C10: BK-001 | D10: 1-105 | E10: Sewa Dibayar Dimuka | F10: ✓ | G10: 24000000 | H10: 0 | I10: Sewa 3 Tahun (36 Bulan)
B11: 03/01 | C11: BK-001 | D11: 1-101 | E11: Kas | F11: ✓ | G11: 0 | H11: 24000000
B12: 05/01 | C12: BK-002 | D12: 1-104 | E12: Perlengkapan Kantor | F12: ✓ | G12: 6500000 | H12: 0 | I12: Perlengkapan Tunai
B13: 05/01 | C13: BK-002 | D13: 1-101 | E13: Kas | F13: ✓ | G13: 0 | H13: 6500000
B14: 10/01 | C14: FJ-001 | D14: 1-102 | E14: Piutang Usaha (PT ABC) | F14: ✓ | G14: 38850000 | H14: 0 | I14: Termin Kredit 30 Hari
B15: 10/01 | C15: FJ-001 | D15: 4-101 | E15: Pendapatan Jasa | F15: ✓ | G15: 0 | H15: 35000000 | I15: DPP
B16: 10/01 | C16: FJ-001 | D16: 2-104 | E16: PPN Keluaran (11%) | F16: ✓ | G16: 0 | H16: 3850000 | I16: =G15*11% (PPN 11%)
B17: 15/01 | C17: FJ-002 | D17: 1-102 | E17: Piutang Usaha (CV DEF) | F17: ✓ | G17: 8880000 | H17: 0 | I17: Termin Kredit 14 Hari
B18: 15/01 | C18: FJ-002 | D18: 4-101 | E18: Pendapatan Jasa | F18: ✓ | G18: 0 | H18: 8000000 | I18: DPP
B19: 15/01 | C19: FJ-002 | D19: 2-104 | E19: PPN Keluaran (11%) | F19: ✓ | G19: 0 | H19: 880000 | I19: =G18*11% (PPN 11%)
B20: 18/01 | C20: FB-001 | D20: 1-103 | E20: Peralatan Kantor | F20: ✓ | G20: 12000000 | H20: 0 | I20: Beli Komputer & Printer
B21: 18/01 | C21: FB-001 | D21: 1-106 | E21: PPN Masukan (11%) | F21: ✓ | G21: 1320000 | H21: 0 | I21: Dapat Dikreditkan
B22: 18/01 | C22: FB-001 | D22: 2-102 | E22: Utang Usaha (CV XYZ) | F22: ✓ | G22: 0 | H22: 13320000
B23: 22/01 | C23: KM-003 | D23: 1-101 | E23: Kas | F23: ✓ | G23: 15000000 | H23: 0 | I23: Pelunasan Sebagian PT ABC
B24: 22/01 | C24: KM-003 | D24: 1-102 | E24: Piutang Usaha (PT ABC) | F24: ✓ | G24: 0 | H24: 15000000
B25: 28/01 | C25: BK-003 | D25: 5-101 | E25: Beban Gaji Karyawan | F25: ✓ | G25: 6500000 | H25: 0 | I25: Gaji Staff Bulan Jan
B26: 28/01 | C26: BK-003 | D26: 1-101 | E26: Kas | F26: ✓ | G26: 0 | H26: 6500000
B27: 30/01 | C27: BK-004 | D27: 5-102 | E27: Beban Listrik & Telepon | F27: ✓ | G27: 1200000 | H27: 0 | I27: Beban Kantor
B28: 30/01 | C28: BK-004 | D28: 1-101 | E28: Kas | F28: ✓ | G28: 0 | H28: 1200000
B29: TOTAL JURNAL UMUM | G29: =SUM(G6:G28) | H29: =SUM(H6:H28)
B30: STATUS KESEIMBANGAN (CEK BALANCE) | G30: =IF(G29=H29, "✓ BALANCE", "⚠️ TIDAK BALANCE")

Sheet 5. Buku_Besar
B2: PT MAJU BERSAMA - BUKU BESAR (GENERAL LEDGER)
B3: Periode: Januari 2025
B5: Akun: 1-101 Kas
B6: Tgl | C6: No. Bukti | D6: Keterangan | E6: Ref | F6: Debet (Rp) | G6: Kredit (Rp) | H6: Saldo Berjalan (Rp)
B7: 01/01 | C7: KM-001 | D7: Setoran Modal Awal | E7: JU-1 | F7: 100000000 | G7: 0 | H7: =F7-G7
B8: 02/01 | C8: KM-002 | D8: Pinjaman Bank KMK | E8: JU-1 | F8: 50000000 | G8: 0 | H8: =H7+F8-G8
B9: 03/01 | C9: BK-001 | D9: Sewa Gedung Dimuka 3 Thn | E9: JU-1 | F9: 0 | G9: 24000000 | H9: =H8+F9-G9
B10: 05/01 | C10: BK-002 | D10: Beli Perlengkapan Tunai | E10: JU-1 | F10: 0 | G10: 6500000 | H10: =H9+F10-G10
B11: 22/01 | C11: KM-003 | D11: Pelunasan Piutang PT ABC | E11: JU-1 | F11: 15000000 | G11: 0 | H11: =H10+F11-G11
B12: 28/01 | C12: BK-003 | D12: Beban Gaji Karyawan | E12: JU-1 | F12: 0 | G12: 6500000 | H12: =H11+F12-G12
B13: 30/01 | C13: BK-004 | D13: Beban Listrik & Telepon | E13: JU-1 | F13: 0 | G13: 1200000 | H13: =H12+F13-G13
B14: SALDO AKHIR KAS (1-101) | H14: =H13
B16: Akun: 1-102 Piutang Usaha
B17: Tgl | C17: No. Bukti | D17: Keterangan | E17: Ref | F17: Debet (Rp) | G17: Kredit (Rp) | H17: Saldo Berjalan (Rp)
B18: 10/01 | C18: FJ-001 | D18: Penjualan Jasa PT ABC | E18: JU-1 | F18: 38850000 | G18: 0 | H18: =F18-G18
B19: 15/01 | C19: FJ-002 | D19: Penjualan Jasa CV DEF | E19: JU-1 | F19: 8880000 | G19: 0 | H19: =H18+F19-G19
B20: 22/01 | C20: KM-003 | D20: Pelunasan Piutang PT ABC | E20: JU-1 | F20: 0 | G20: 15000000 | H20: =H19+F20-G20
B21: SALDO AKHIR PIUTANG (1-102) | H21: =H20

Sheet 6. Neraca_Saldo
B2: PT MAJU BERSAMA - NERACA SALDO SEBELUM PENYESUAIAN
B3: Per 31 Januari 2025
B5: Kode Akun | C5: Nama Akun | D5: Debet (Rp) | E5: Kredit (Rp) | F5: Formula / Sumber Saldo
B6: 1-101 | C6: Kas | D6: ='5. Buku_Besar'!H14 | E6: 0 | F6: Buku Besar Kas
B7: 1-102 | C7: Piutang Usaha | D7: ='5. Buku_Besar'!H21 | E7: 0 | F7: Buku Besar Piutang
B8: 1-103 | C8: Peralatan Kantor | D8: 12000000 | E8: 0 | F8: Faktur FB-001
B9: 1-104 | C9: Perlengkapan Kantor | D9: 6500000 | E9: 0 | F9: Bukti BK-002
B10: 1-105 | C10: Sewa Dibayar Dimuka | D10: 24000000 | E10: 0 | F10: Bukti BK-001
B11: 1-106 | C11: PPN Masukan (11%) | D11: 1320000 | E11: 0 | F11: Faktur FB-001
B12: 2-101 | C12: Utang Bank (KMK) | D12: 0 | E12: 50000000 | F12: Bukti KM-002
B13: 2-102 | C13: Utang Usaha (CV XYZ) | D13: 0 | E13: 13320000 | F13: Faktur FB-001
B14: 2-104 | C14: PPN Keluaran (11%) | D14: 0 | E14: 4730000 | F14: FJ-001 & FJ-002
B15: 3-101 | C15: Modal Pemilik | D15: 0 | E15: 100000000 | F15: Bukti KM-001
B16: 4-101 | C16: Pendapatan Jasa | D16: 0 | E16: 43000000 | F16: FJ-001 & FJ-002
B17: 5-101 | C17: Beban Gaji Karyawan | D17: 6500000 | E17: 0 | F17: Bukti BK-003
B18: 5-102 | C18: Beban Listrik & Telepon | D18: 1200000 | E18: 0 | F18: Bukti BK-004
B19: TOTAL NERACA SALDO | D19: =SUM(D6:D18) | E19: =SUM(E6:E18)
B20: STATUS KESEIMBANGAN | D20: =IF(D19=E19, "✓ BALANCE", "⚠️ TIDAK BALANCE")

Sheet 7. Jurnal_Penyesuaian
B2: PT MAJU BERSAMA - JURNAL PENYESUAIAN
B3: per 31 Januari 2025
B5: No. Bukti | C5: Kode Akun | D5: Nama Akun | E5: Debet (Rp) | F5: Kredit (Rp) | G5: Catatan / Keterangan Penyesuaian
B6: AJP-001 | C6: 5-103 | D6: Beban Sewa | E6: =24000000/36 | F6: 0 | G6: Sewa gedung 1 bln (24jt / 36 bln)
B7: AJP-001 | C7: 1-105 | D7: Sewa Dibayar Dimuka | E7: 0 | F7: =24000000/36
B8: AJP-002 | C8: 5-104 | D8: Beban Perlengkapan | E8: =6500000-4000000 | F8: 0 | G8: Perlengkapan terpakai (6.5jt - sisa 4jt)
B9: AJP-002 | C9: 1-104 | D9: Perlengkapan Kantor | E9: 0 | F9: =6500000-4000000
B10: AJP-003 | C10: 5-105 | D10: Beban Depresiasi Peralatan | E10: =SLN(12000000, 0, 60) | F10: 0 | G10: Depresiasi SLN (12jt / 5 th / 12 bln)
B11: AJP-003 | C11: 1-103.1 | D11: Akum. Depresiasi Peralatan | E11: 0 | F11: =SLN(12000000, 0, 60)
B12: AJP-004 | C12: 5-106 | D12: Beban Bunga Bank | E12: =50000000*1% | F12: 0 | G12: Bunga pinjaman bank (1% x 50jt)
B13: AJP-004 | C13: 2-103 | D13: Utang Bunga | E13: 0 | F13: =50000000*1%
B14: AJP-005 | C14: 1-101 | D14: Kas di Bank | E14: 320000 | F14: 0 | G14: Jasa giro bank rekening koran
B15: AJP-005 | C15: 4-102 | D15: Pendapatan Jasa Giro Bank | E15: 0 | F15: 320000
B16: AJP-006 | C16: 5-107 | D16: Beban Administrasi Bank | E16: 25000 | F16: 0 | G16: Biaya admin bank per rekening koran
B17: AJP-006 | C17: 1-101 | D17: Kas di Bank | E17: 0 | F17: 25000
B18: AJP-007 | C18: 5-108 | D18: Beban Kerugian Piutang | E18: =32730000*1% | F18: 0 | G18: Taksiran cadangan kerugian (1% piutang)
B19: AJP-007 | C19: 1-102.1 | D19: Cadangan Kerugian Piutang | E19: 0 | F19: =32730000*1%
B20: TOTAL AJP | E20: =SUM(E6:E19) | F20: =SUM(F6:F19)
B21: CEK (Debet - Kredit) | E21: =IF(ROUND(E20,0)=ROUND(F20,0), "✓ BALANCE", "⚠️ TIDAK BALANCE")

Sheet 8. Kertas_Kerja_10_Kolom
B2: PT MAJU BERSAMA - KERTAS KERJA / NERACA LAJUR (WORKSHEET 10 KOLOM)
B3: Per 31 Januari 2025
B5: Kode | C5: Nama Akun | D5: Neraca Saldo | F5: Penyesuaian (AJP) | H5: NS Disesuaikan (NSD) | J5: Laba / Rugi | L5: Neraca Akhir
D6: Debet | E6: Kredit | F6: Debet | G6: Kredit | H6: Debet | I6: Kredit | J6: Debet | K6: Kredit | L6: Debet | M6: Kredit
B7: 1-101 | C7: Kas | D7: 101800000 | E7: 0 | F7: 320000 | G7: 25000 | H7: =MAX(0, D7-E7+F7-G7) | I7: =MAX(0, E7-D7+G7-F7) | J7: =IF(LEFT(B7,1)="5", H7, 0) | K7: =IF(LEFT(B7,1)="4", I7, 0) | L7: =IF(LEFT(B7,1)="1", H7, 0) | M7: =IF(OR(LEFT(B7,1)="2",LEFT(B7,1)="3",B7="1-102.1",B7="1-103.1"), I7, 0)
B8: 1-102 | C8: Piutang Usaha | D8: 32730000 | E8: 0 | F8: 0 | G8: 0 | H8: =MAX(0, D8-E8+F8-G8) | I8: =MAX(0, E8-D8+G8-F8) | J8: =IF(LEFT(B8,1)="5", H8, 0) | K8: =IF(LEFT(B8,1)="4", I8, 0) | L8: =IF(LEFT(B8,1)="1", H8, 0) | M8: =IF(OR(LEFT(B8,1)="2",LEFT(B8,1)="3",B8="1-102.1",B8="1-103.1"), I8, 0)
B9: 1-102.1 | C9: Cadangan Kerugian Piutang | D9: 0 | E9: 0 | F9: 0 | G9: 327300 | H9: =MAX(0, D9-E9+F9-G9) | I9: =MAX(0, E9-D9+G9-F9) | J9: =IF(LEFT(B9,1)="5", H9, 0) | K9: =IF(LEFT(B9,1)="4", I9, 0) | L9: =IF(LEFT(B9,1)="1", H9, 0) | M9: =IF(OR(LEFT(B9,1)="2",LEFT(B9,1)="3",B9="1-102.1",B9="1-103.1"), I9, 0)
B10: 1-103 | C10: Peralatan Kantor | D10: 12000000 | E10: 0 | F10: 0 | G10: 0 | H10: =MAX(0, D10-E10+F10-G10) | I10: =MAX(0, E10-D10+G10-F10) | J10: =IF(LEFT(B10,1)="5", H10, 0) | K10: =IF(LEFT(B10,1)="4", I10, 0) | L10: =IF(LEFT(B10,1)="1", H10, 0) | M10: =IF(OR(LEFT(B10,1)="2",LEFT(B10,1)="3",B10="1-102.1",B10="1-103.1"), I10, 0)
B11: 1-103.1 | C11: Akum. Depresiasi Peralatan | D11: 0 | E11: 0 | F11: 0 | G11: 200000 | H11: =MAX(0, D11-E11+F11-G11) | I11: =MAX(0, E11-D11+G11-F11) | J11: =IF(LEFT(B11,1)="5", H11, 0) | K11: =IF(LEFT(B11,1)="4", I11, 0) | L11: =IF(LEFT(B11,1)="1", H11, 0) | M11: =IF(OR(LEFT(B11,1)="2",LEFT(B11,1)="3",B11="1-102.1",B11="1-103.1"), I11, 0)
B12: 1-104 | C12: Perlengkapan Kantor | D12: 6500000 | E12: 0 | F12: 0 | G12: 2500000 | H12: =MAX(0, D12-E12+F12-G12) | I12: =MAX(0, E12-D12+G12-F12) | J12: =IF(LEFT(B12,1)="5", H12, 0) | K12: =IF(LEFT(B12,1)="4", I12, 0) | L12: =IF(LEFT(B12,1)="1", H12, 0) | M12: =IF(OR(LEFT(B12,1)="2",LEFT(B12,1)="3",B12="1-102.1",B12="1-103.1"), I12, 0)
B13: 1-105 | C13: Sewa Dibayar Dimuka | D13: 24000000 | E13: 0 | F13: 0 | G13: 666667 | H13: =MAX(0, D13-E13+F13-G13) | I13: =MAX(0, E13-D13+G13-F13) | J13: =IF(LEFT(B13,1)="5", H13, 0) | K13: =IF(LEFT(B13,1)="4", I13, 0) | L13: =IF(LEFT(B13,1)="1", H13, 0) | M13: =IF(OR(LEFT(B13,1)="2",LEFT(B13,1)="3",B13="1-102.1",B13="1-103.1"), I13, 0)
B14: 1-106 | C14: PPN Masukan (11%) | D14: 1320000 | E14: 0 | F14: 0 | G14: 0 | H14: =MAX(0, D14-E14+F14-G14) | I14: =MAX(0, E14-D14+G14-F14) | J14: =IF(LEFT(B14,1)="5", H14, 0) | K14: =IF(LEFT(B14,1)="4", I14, 0) | L14: =IF(LEFT(B14,1)="1", H14, 0) | M14: =IF(OR(LEFT(B14,1)="2",LEFT(B14,1)="3",B14="1-102.1",B14="1-103.1"), I14, 0)
B15: 2-101 | C15: Utang Bank (KMK) | D15: 0 | E15: 50000000 | F15: 0 | G15: 0 | H15: =MAX(0, D15-E15+F15-G15) | I15: =MAX(0, E15-D15+G15-F15) | J15: =IF(LEFT(B15,1)="5", H15, 0) | K15: =IF(LEFT(B15,1)="4", I15, 0) | L15: =IF(LEFT(B15,1)="1", H15, 0) | M15: =IF(OR(LEFT(B15,1)="2",LEFT(B15,1)="3",B15="1-102.1",B15="1-103.1"), I15, 0)
B16: 2-102 | C16: Utang Usaha (CV XYZ) | D16: 0 | E16: 13320000 | F16: 0 | G16: 0 | H16: =MAX(0, D16-E16+F16-G16) | I16: =MAX(0, E16-D16+G16-F16) | J16: =IF(LEFT(B16,1)="5", H16, 0) | K16: =IF(LEFT(B16,1)="4", I16, 0) | L16: =IF(LEFT(B16,1)="1", H16, 0) | M16: =IF(OR(LEFT(B16,1)="2",LEFT(B16,1)="3",B16="1-102.1",B16="1-103.1"), I16, 0)
B17: 2-103 | C17: Utang Bunga | D17: 0 | E17: 0 | F17: 0 | G17: 500000 | H17: =MAX(0, D17-E17+F17-G17) | I17: =MAX(0, E17-D17+G17-F17) | J17: =IF(LEFT(B17,1)="5", H17, 0) | K17: =IF(LEFT(B17,1)="4", I17, 0) | L17: =IF(LEFT(B17,1)="1", H17, 0) | M17: =IF(OR(LEFT(B17,1)="2",LEFT(B17,1)="3",B17="1-102.1",B17="1-103.1"), I17, 0)
B18: 2-104 | C18: PPN Keluaran (11%) | D18: 0 | E18: 4730000 | F18: 0 | G18: 0 | H18: =MAX(0, D18-E18+F18-G18) | I18: =MAX(0, E18-D18+G18-F18) | J18: =IF(LEFT(B18,1)="5", H18, 0) | K18: =IF(LEFT(B18,1)="4", I18, 0) | L18: =IF(LEFT(B18,1)="1", H18, 0) | M18: =IF(OR(LEFT(B18,1)="2",LEFT(B18,1)="3",B18="1-102.1",B18="1-103.1"), I18, 0)
... B29: 5-108 | C29: Beban Kerugian Piutang | D29: 0 | E29: 0 | F29: 327300 | G29: 0 | H29: =MAX(0, D29-E29+F29-G29) | I29: =MAX(0, E29-D29+G29-F29) | J29: =IF(LEFT(B29,1)="5", H29, 0) | K29: =IF(LEFT(B29,1)="4", I29, 0) | L29: =IF(LEFT(B29,1)="1", H29, 0) | M29: =IF(OR(LEFT(B29,1)="2",LEFT(B29,1)="3",B29="1-102.1",B29="1-103.1"), I29, 0)
B30: TOTAL SIKLUS | D30: =SUM(D7:D29) | E30: =SUM(E7:E29) | F30: =SUM(F7:F29) | G30: =SUM(G7:G29) | H30: =SUM(H7:H29) | I30: =SUM(I7:I29) | J30: =SUM(J7:J29) | K30: =SUM(K7:K29) | ... M30: =SUM(M7:M29)
B31: LABA BERSIH BULAN BERJALAN | J31: =K30-J30 | M31: =L30-M30

Sheet 9. Laporan_Laba_Rugi
B2: PT MAJU BERSAMA
B3: LAPORAN LABA RUGI KOMPREHENSIF
B4: Untuk Periode yang Berakhir 31 Januari 2025
B6: I. PENDAPATAN OPERASIONAL
B7: Pendapatan Jasa Konsultasi | C7: ='8. Kertas_Kerja_10_Kolom'!K20
B8: Pendapatan Jasa Giro Bank | C8: ='8. Kertas_Kerja_10_Kolom'!K21
B9: TOTAL PENDAPATAN | D9: =SUM(C7:C8)
B11: II. BEBAN OPERASIONAL
B12: Beban Gaji Karyawan | C12: ='8. Kertas_Kerja_10_Kolom'!J22
B13: Beban Listrik & Telepon | C13: ='8. Kertas_Kerja_10_Kolom'!J23
B14: Beban Sewa Gedung | C14: ='8. Kertas_Kerja_10_Kolom'!J24
B15: Beban Perlengkapan Kantor | C15: ='8. Kertas_Kerja_10_Kolom'!J25
B16: Beban Depresiasi Peralatan | C16: ='8. Kertas_Kerja_10_Kolom'!J26
B17: Beban Bunga Pinjaman Bank | C17: ='8. Kertas_Kerja_10_Kolom'!J27
B18: Beban Administrasi Bank | C18: ='8. Kertas_Kerja_10_Kolom'!J28
B19: Beban Kerugian Piutang | C19: ='8. Kertas_Kerja_10_Kolom'!J29
B20: TOTAL BEBAN OPERASIONAL | D20: =SUM(C12:C19)
B22: LABA BERSIH USAHA (NET INCOME) | D22: =D9-D20

Sheet 10. Laporan_Perubahan_Modal
B2: PT MAJU BERSAMA
B3: LAPORAN PERUBAHAN MODAL
B4: Untuk Periode yang Berakhir 31 Januari 2025
B6: Modal Awal Pemilik (1 Januari 2025) | D6: 100000000
B7: Laba Bersih Bulan Januari 2025 | D7: ='9. Laporan_Laba_Rugi'!D22
B8: Penarikan Prive Pemilik | D8: 0
B10: MODAL AKHIR PEMILIK (31 Januari 2025) | D10: =D6+D7-D8

Sheet 11. Neraca_Keuangan
B2: PT MAJU BERSAMA
B3: LAPORAN POSISI KEUANGAN (NERACA)
B4: Per 31 Januari 2025
B6: ASET LANCAR | F6: KEWAJIBAN LANCAR
B7: Kas dan Setara Kas | C7: ='8. Kertas_Kerja_10_Kolom'!L7 | F7: Utang Usaha (CV XYZ) | G7: ='8. Kertas_Kerja_10_Kolom'!M16
B8: Piutang Usaha | C8: ='8. Kertas_Kerja_10_Kolom'!L8 | F8: Utang Bunga Akrual | G8: ='8. Kertas_Kerja_10_Kolom'!M17
B9: Cadangan Kerugian Piutang | C9: =-'8. Kertas_Kerja_10_Kolom'!M9 | F9: Utang PPN Keluaran | G9: ='8. Kertas_Kerja_10_Kolom'!M18
B10: Perlengkapan Kantor | C10: ='8. Kertas_Kerja_10_Kolom'!L12 | F10: TOTAL KEWAJIBAN LANCAR | H10: =SUM(G7:G9)
B11: Sewa Dibayar Dimuka | C11: ='8. Kertas_Kerja_10_Kolom'!L13
B12: PPN Masukan | C12: ='8. Kertas_Kerja_10_Kolom'!L14 | F12: KEWAJIBAN JANGKA PANJANG
B13: TOTAL ASET LANCAR | D13: =SUM(C7:C12) | F13: Utang Bank (KMK) | H13: ='8. Kertas_Kerja_10_Kolom'!M15
B15: ASET TETAP | F15: EKUITAS PEMILIK
B16: Peralatan Kantor | C16: ='8. Kertas_Kerja_10_Kolom'!L10 | F16: Modal Akhir Pemilik | H16: ='10. Laporan_Perubahan_Modal'!D10
B17: Akumulasi Depresiasi Peralatan | C17: =-'8. Kertas_Kerja_10_Kolom'!M11
B18: TOTAL ASET TETAP BERSIH | D18: =SUM(C16:C17)
B20: TOTAL ASET (AKTIVA) | D20: =D13+D18 | F20: TOTAL KEWAJIBAN & EKUITAS (PASIVA) | H20: =H10+H13+H16
B22: STATUS NERACA (AKTIVA = PASIVA): | D22: =IF(D20=H20, "✓ BALANCE (AKTIVA = PASIVA)", "⚠️ TIDAK BALANCE")

Sheet 99_KUNCI_JAWABAN
B2: KUNCI JAWABAN RESMI & FORMULA LENGKAP SIMULASI AKUNTANSI
B3: Panduan Pendidik, Penguji Tes Kerja, & Kunci Evaluasi Mandiri
B5: No | C5: Sheet / Kasus | D5: Pertanyaan / Tugas | E5: Kunci Jawaban Resmi / Ayat Jurnal | F5: Rumus Excel yang Digunakan | G5: Nalar & Logika Akuntansi
B6: 1 | C6: 2. Soal_Interview_Akunting | D6: 1 Mei: Setoran modal tunai 50jt | E6: Debet: Kas Rp50.000.000 | Kredit: Modal Rp50.000.000 | F6: =SUM(), =IF() | G6: Kas bertambah di Debet, hak pemilik bertambah di Kredit.
B7: 2 | C7: 2. Soal_Interview_Akunting | D7: 2 Mei: Beli perlengkapan tunai 3.5jt | E7: Debet: Perlengkapan Rp3.500.000 | Kredit: Kas Rp3.500.000 | F7: - | G7: Aset perlengkapan bertambah, aset kas berkurang secara tunai.
B8: 3 | C8: 2. Soal_Interview_Akunting | D8: 3 Mei: Beli barang kredit PT Sumber Jaya 15jt | E8: Debet: Pembelian Rp15.000.000 | Kredit: Utang Usaha Rp15.000.000 | F8: - | G8: Barang dagang masuk, kewajiban utang dagang bertambah.
B9: 4 | C9: 2. Soal_Interview_Akunting | D9: 5 Mei: Jual tunai 8jt | E9: Debet: Kas Rp8.000.000 | Kredit: Penjualan Rp8.000.000 | F9: - | G9: Pendapatan diakui di kredit, kas bertambah di debet.
B10: 5 | C10: 2. Soal_Interview_Akunting | D10: 10 Mei: Bayar utang 5jt transfer | E10: Debet: Utang Usaha Rp5.000.000 | Kredit: Kas di Bank Rp5.000.000 | F10: - | G10: Utang dilunasi (berkurang di debet), rekening bank berkurang di kredit.
B11: 6 | C11: 2. Soal_Interview_Akunting | D11: 12 Mei: Beban listrik & air 750rb tunai | E11: Debet: Beban Listrik & Air Rp750.000 | Kredit: Kas Rp750.000 | F11: - | G11: Beban mengurangi laba di debet, kas berkurang di kredit.
B12: 7 | C12: 2. Soal_Interview_Akunting | D12: 15 Mei: Prive pemilik 2jt | E12: Debet: Prive Pemilik Rp2.000.000 | Kredit: Kas Rp2.000.000 | F12: - | G12: Penarikan pribadi pemilik mengurangi ekuitas di debet.
B13: 8 | C13: 4. Jurnal_Umum | D13: PPN Keluaran 11% Faktur FJ-001 (DPP 35jt) | E13: PPN = Rp3.850.000, Total Piutang = Rp38.850.000 | F13: =G15*11%, =SUM(G15:H16) | G13: Tarif PPN 11% resmi Indonesia atas penyerahan BKP/JKP.
B14: 9 | C14: 5. Buku_Besar | D14: Formula Saldo Berjalan Kas (Running Balance) | E14: Debet menambah saldo, Kredit mengurangi saldo | F14: =H6+F7-G7 | G14: Aktiva bersaldo normal debet: Saldo baru = Saldo lalu + Debet - Kredit.
B15: 10 | C15: 6. Neraca_Saldo | D15: Keseimbangan Neraca Saldo | E15: Debet = Rp198.850.000 | Kredit = Rp198.850.000 | F15: =IF(D19=E19, "✓ BALANCE", "⚠️ TIDAK") | G15: Jumlah debet seluruh buku besar wajib persis sama dengan kredit.
B16: 11 | C16: 7. Jurnal_Penyesuaian | D16: AJP Sewa Gedung Bulanan (36 Bulan) | E16: Debet: Beban Sewa Rp666.667 | Kredit: Sewa Dimuka Rp666.667 | F16: =24000000/36 | G16: Prinsip penandingan (matching principle): Beban diakui per bulan berlalu.
B17: 12 | C17: 7. Jurnal_Penyesuaian | D17: AJP Depresiasi Garis Lurus Peralatan | E17: Debet: Beban Depresiasi Rp200.000 | Kredit: Akum Depresiasi Rp200.000 | F17: =SLN(12000000, 0, 60) | G17: Rumus Excel SLN(Cost, Salvage, Life) membagi biaya aset secara merata.
B18: 13 | C18: 7. Jurnal_Penyesuaian | D18: AJP Bunga Pinjaman Bank Akrual | E18: Debet: Beban Bunga Rp500.000 | Kredit: Utang Bunga Rp500.000 | F18: =50000000*1% | G18: Bunga yang sudah menjadi kewajiban bulan Januari tetapi belum dibayar.
B19: 14 | C19: 9. Laporan_Laba_Rugi | D19: Perhitungan Laba Bersih Usaha | E19: Laba Bersih = Total Pendapatan - Total Beban Operasional | F19: =D9-D20 | G19: Mengukur profitabilitas riil perusahaan selama periode berjalan.
B20: 15 | C20: 11. Neraca_Keuangan | D20: Persamaan Dasar Akuntansi Neraca | E20: Aset (Aktiva) = Kewajiban + Ekuitas (Pasiva) | F20: =IF(D20=H20, "✓ BALANCE", "⚠️") | G20: Prinsip dualitas akuntansi Italia kuno Luca Pacioli yang mutlak seimbang.
